[
    {
        "colo": "Default",
        "ip": "2606:4700:99ed:a815:9b6e:555d:e398:4cc3",
        "latency": 4,
        "line": "CM",
        "loss": 0,
        "node": "NETCUP",
        "speed": 576,
        "time": "2025-06-22 21:26:40"
    },
    {
        "colo": "Default",
        "ip": "2606:4700:3034:af1a:9e61:9a68:540d:785b",
        "latency": 13,
        "line": "CM",
        "loss": 0,
        "node": "NETCUP",
        "speed": 533,
        "time": "2025-06-22 21:26:39"
    },
    {
        "colo": "Default",
        "ip": "2606:4700:8d71:17ab:6d5d:6e90:a0d9:8c1b",
        "latency": 3,
        "line": "CM",
        "loss": 0,
        "node": "NETCUP",
        "speed": 507,
        "time": "2025-06-22 21:26:39"
    },
    {
        "colo": "Default",
        "ip": "2606:4700:8d71:bbfe:1ee6:f3c:baab:4255",
        "latency": 3,
        "line": "CM",
        "loss": 0,
        "node": "NETCUP",
        "speed": 416,
        "time": "2025-06-22 21:26:39"
    },
    {
        "colo": "Default",
        "ip": "2606:4700:9646:5312:e892:a7d4:9b89:c940",
        "latency": 4,
        "line": "CM",
        "loss": 0,
        "node": "NETCUP",
        "speed": 351,
        "time": "2025-06-22 21:26:40"
    },
    {
        "colo": "Default",
        "ip": "2606:4700:99ed:a815:9b6e:555d:e398:4cc3",
        "latency": 4,
        "line": "CT",
        "loss": 0,
        "node": "NETCUP",
        "speed": 576,
        "time": "2025-06-22 21:26:40"
    },
    {
        "colo": "Default",
        "ip": "2606:4700:3034:af1a:9e61:9a68:540d:785b",
        "latency": 13,
        "line": "CT",
        "loss": 0,
        "node": "NETCUP",
        "speed": 533,
        "time": "2025-06-22 21:26:39"
    },
    {
        "colo": "Default",
        "ip": "2606:4700:8d71:17ab:6d5d:6e90:a0d9:8c1b",
        "latency": 3,
        "line": "CT",
        "loss": 0,
        "node": "NETCUP",
        "speed": 507,
        "time": "2025-06-22 21:26:39"
    },
    {
        "colo": "Default",
        "ip": "2606:4700:8d71:bbfe:1ee6:f3c:baab:4255",
        "latency": 3,
        "line": "CT",
        "loss": 0,
        "node": "NETCUP",
        "speed": 416,
        "time": "2025-06-22 21:26:39"
    },
    {
        "colo": "Default",
        "ip": "2606:4700:9646:5312:e892:a7d4:9b89:c940",
        "latency": 4,
        "line": "CT",
        "loss": 0,
        "node": "NETCUP",
        "speed": 351,
        "time": "2025-06-22 21:26:40"
    },
    {
        "colo": "Default",
        "ip": "2606:4700:99ed:a815:9b6e:555d:e398:4cc3",
        "latency": 4,
        "line": "CU",
        "loss": 0,
        "node": "NETCUP",
        "speed": 576,
        "time": "2025-06-22 21:26:40"
    },
    {
        "colo": "Default",
        "ip": "2606:4700:3034:af1a:9e61:9a68:540d:785b",
        "latency": 13,
        "line": "CU",
        "loss": 0,
        "node": "NETCUP",
        "speed": 533,
        "time": "2025-06-22 21:26:39"
    },
    {
        "colo": "Default",
        "ip": "2606:4700:8d71:17ab:6d5d:6e90:a0d9:8c1b",
        "latency": 3,
        "line": "CU",
        "loss": 0,
        "node": "NETCUP",
        "speed": 507,
        "time": "2025-06-22 21:26:39"
    },
    {
        "colo": "Default",
        "ip": "2606:4700:8d71:bbfe:1ee6:f3c:baab:4255",
        "latency": 3,
        "line": "CU",
        "loss": 0,
        "node": "NETCUP",
        "speed": 416,
        "time": "2025-06-22 21:26:39"
    },
    {
        "colo": "Default",
        "ip": "2606:4700:9646:5312:e892:a7d4:9b89:c940",
        "latency": 4,
        "line": "CU",
        "loss": 0,
        "node": "NETCUP",
        "speed": 351,
        "time": "2025-06-22 21:26:40"
    }
]