[
    {
        "colo": "Default",
        "ip": "2606:4700:9ad6:f969:4003:5224:675a:b495",
        "latency": 3,
        "line": "CM",
        "loss": 0,
        "node": "NETCUP",
        "speed": 606,
        "time": "2025-09-09 05:29:48"
    },
    {
        "colo": "Default",
        "ip": "2606:4700:90ca:568:2e49:72bc:8599:fbb",
        "latency": 3,
        "line": "CM",
        "loss": 0,
        "node": "NETCUP",
        "speed": 602,
        "time": "2025-09-09 05:29:47"
    },
    {
        "colo": "Default",
        "ip": "2606:4700:131:a99d:4b70:ea06:ee9a:dfe3",
        "latency": 3,
        "line": "CM",
        "loss": 0,
        "node": "NETCUP",
        "speed": 584,
        "time": "2025-09-09 05:29:47"
    },
    {
        "colo": "Default",
        "ip": "2606:4700:131:960c:88c8:7e70:7b8e:b41f",
        "latency": 4,
        "line": "CM",
        "loss": 0,
        "node": "NETCUP",
        "speed": 406,
        "time": "2025-09-09 05:29:47"
    },
    {
        "colo": "Default",
        "ip": "2606:4700:8ca7:fd79:d497:bfb:5306:27f",
        "latency": 3,
        "line": "CM",
        "loss": 0,
        "node": "NETCUP",
        "speed": 403,
        "time": "2025-09-09 05:29:47"
    },
    {
        "colo": "Default",
        "ip": "2606:4700:9ad6:f969:4003:5224:675a:b495",
        "latency": 3,
        "line": "CT",
        "loss": 0,
        "node": "NETCUP",
        "speed": 606,
        "time": "2025-09-09 05:29:48"
    },
    {
        "colo": "Default",
        "ip": "2606:4700:90ca:568:2e49:72bc:8599:fbb",
        "latency": 3,
        "line": "CT",
        "loss": 0,
        "node": "NETCUP",
        "speed": 602,
        "time": "2025-09-09 05:29:47"
    },
    {
        "colo": "Default",
        "ip": "2606:4700:131:a99d:4b70:ea06:ee9a:dfe3",
        "latency": 3,
        "line": "CT",
        "loss": 0,
        "node": "NETCUP",
        "speed": 584,
        "time": "2025-09-09 05:29:47"
    },
    {
        "colo": "Default",
        "ip": "2606:4700:131:960c:88c8:7e70:7b8e:b41f",
        "latency": 4,
        "line": "CT",
        "loss": 0,
        "node": "NETCUP",
        "speed": 406,
        "time": "2025-09-09 05:29:47"
    },
    {
        "colo": "Default",
        "ip": "2606:4700:8ca7:fd79:d497:bfb:5306:27f",
        "latency": 3,
        "line": "CT",
        "loss": 0,
        "node": "NETCUP",
        "speed": 403,
        "time": "2025-09-09 05:29:47"
    },
    {
        "colo": "Default",
        "ip": "2606:4700:9ad6:f969:4003:5224:675a:b495",
        "latency": 3,
        "line": "CU",
        "loss": 0,
        "node": "NETCUP",
        "speed": 606,
        "time": "2025-09-09 05:29:48"
    },
    {
        "colo": "Default",
        "ip": "2606:4700:90ca:568:2e49:72bc:8599:fbb",
        "latency": 3,
        "line": "CU",
        "loss": 0,
        "node": "NETCUP",
        "speed": 602,
        "time": "2025-09-09 05:29:47"
    },
    {
        "colo": "Default",
        "ip": "2606:4700:131:a99d:4b70:ea06:ee9a:dfe3",
        "latency": 3,
        "line": "CU",
        "loss": 0,
        "node": "NETCUP",
        "speed": 584,
        "time": "2025-09-09 05:29:47"
    },
    {
        "colo": "Default",
        "ip": "2606:4700:131:960c:88c8:7e70:7b8e:b41f",
        "latency": 4,
        "line": "CU",
        "loss": 0,
        "node": "NETCUP",
        "speed": 406,
        "time": "2025-09-09 05:29:47"
    },
    {
        "colo": "Default",
        "ip": "2606:4700:8ca7:fd79:d497:bfb:5306:27f",
        "latency": 3,
        "line": "CU",
        "loss": 0,
        "node": "NETCUP",
        "speed": 403,
        "time": "2025-09-09 05:29:47"
    }
]