[
    {
        "colo": "Default",
        "ip": "2606:4700:9a6b:7a5:5867:3e68:9574:af7",
        "latency": 4,
        "line": "CM",
        "loss": 0,
        "node": "NETCUP",
        "speed": 580,
        "time": "2025-09-17 23:19:51"
    },
    {
        "colo": "Default",
        "ip": "2606:4700:3055:433d:581d:ef6d:a841:6574",
        "latency": 3,
        "line": "CM",
        "loss": 0,
        "node": "NETCUP",
        "speed": 525,
        "time": "2025-09-17 23:19:51"
    },
    {
        "colo": "Default",
        "ip": "2606:4700:3:ae4f:f3fd:9a45:54e0:b12a",
        "latency": 4,
        "line": "CM",
        "loss": 0,
        "node": "NETCUP",
        "speed": 387,
        "time": "2025-09-17 23:19:51"
    },
    {
        "colo": "Default",
        "ip": "2606:4700:9a6b:b438:9aff:ece9:88b:77b6",
        "latency": 3,
        "line": "CM",
        "loss": 0,
        "node": "NETCUP",
        "speed": 352,
        "time": "2025-09-17 23:19:51"
    },
    {
        "colo": "Default",
        "ip": "2606:4700:3:255a:e53f:4a8c:f97f:2e58",
        "latency": 3,
        "line": "CM",
        "loss": 0,
        "node": "NETCUP",
        "speed": 316,
        "time": "2025-09-17 23:19:51"
    },
    {
        "colo": "Default",
        "ip": "2606:4700:9a6b:7a5:5867:3e68:9574:af7",
        "latency": 4,
        "line": "CT",
        "loss": 0,
        "node": "NETCUP",
        "speed": 580,
        "time": "2025-09-17 23:19:51"
    },
    {
        "colo": "Default",
        "ip": "2606:4700:3055:433d:581d:ef6d:a841:6574",
        "latency": 3,
        "line": "CT",
        "loss": 0,
        "node": "NETCUP",
        "speed": 525,
        "time": "2025-09-17 23:19:51"
    },
    {
        "colo": "Default",
        "ip": "2606:4700:3:ae4f:f3fd:9a45:54e0:b12a",
        "latency": 4,
        "line": "CT",
        "loss": 0,
        "node": "NETCUP",
        "speed": 387,
        "time": "2025-09-17 23:19:51"
    },
    {
        "colo": "Default",
        "ip": "2606:4700:9a6b:b438:9aff:ece9:88b:77b6",
        "latency": 3,
        "line": "CT",
        "loss": 0,
        "node": "NETCUP",
        "speed": 352,
        "time": "2025-09-17 23:19:51"
    },
    {
        "colo": "Default",
        "ip": "2606:4700:3:255a:e53f:4a8c:f97f:2e58",
        "latency": 3,
        "line": "CT",
        "loss": 0,
        "node": "NETCUP",
        "speed": 316,
        "time": "2025-09-17 23:19:51"
    },
    {
        "colo": "Default",
        "ip": "2606:4700:9a6b:7a5:5867:3e68:9574:af7",
        "latency": 4,
        "line": "CU",
        "loss": 0,
        "node": "NETCUP",
        "speed": 580,
        "time": "2025-09-17 23:19:51"
    },
    {
        "colo": "Default",
        "ip": "2606:4700:3055:433d:581d:ef6d:a841:6574",
        "latency": 3,
        "line": "CU",
        "loss": 0,
        "node": "NETCUP",
        "speed": 525,
        "time": "2025-09-17 23:19:51"
    },
    {
        "colo": "Default",
        "ip": "2606:4700:3:ae4f:f3fd:9a45:54e0:b12a",
        "latency": 4,
        "line": "CU",
        "loss": 0,
        "node": "NETCUP",
        "speed": 387,
        "time": "2025-09-17 23:19:51"
    },
    {
        "colo": "Default",
        "ip": "2606:4700:9a6b:b438:9aff:ece9:88b:77b6",
        "latency": 3,
        "line": "CU",
        "loss": 0,
        "node": "NETCUP",
        "speed": 352,
        "time": "2025-09-17 23:19:51"
    },
    {
        "colo": "Default",
        "ip": "2606:4700:3:255a:e53f:4a8c:f97f:2e58",
        "latency": 3,
        "line": "CU",
        "loss": 0,
        "node": "NETCUP",
        "speed": 316,
        "time": "2025-09-17 23:19:51"
    }
]