[
    {
        "colo": "Default",
        "ip": "2606:4700:9c6b:670f:1b66:50dd:7e31:d8e3",
        "latency": 3,
        "line": "CM",
        "loss": 0,
        "node": "NETCUP",
        "speed": 622,
        "time": "2025-12-10 09:49:17"
    },
    {
        "colo": "Default",
        "ip": "2606:4700:440a:c652:37e4:22b7:3f50:a9de",
        "latency": 3,
        "line": "CM",
        "loss": 0,
        "node": "NETCUP",
        "speed": 448,
        "time": "2025-12-10 09:49:17"
    },
    {
        "colo": "Default",
        "ip": "2606:4700:9c6b:7a4d:b9ca:19a:a529:1e0",
        "latency": 3,
        "line": "CM",
        "loss": 0,
        "node": "NETCUP",
        "speed": 392,
        "time": "2025-12-10 09:49:17"
    },
    {
        "colo": "Default",
        "ip": "2606:4700:440a:1f16:ef42:9875:67b7:6289",
        "latency": 5,
        "line": "CM",
        "loss": 0,
        "node": "NETCUP",
        "speed": 373,
        "time": "2025-12-10 09:49:17"
    },
    {
        "colo": "Default",
        "ip": "2606:4700:3027:8c48:d109:4ab1:83cb:612c",
        "latency": 3,
        "line": "CM",
        "loss": 0,
        "node": "NETCUP",
        "speed": 361,
        "time": "2025-12-10 09:49:17"
    },
    {
        "colo": "Default",
        "ip": "2606:4700:9c6b:670f:1b66:50dd:7e31:d8e3",
        "latency": 3,
        "line": "CT",
        "loss": 0,
        "node": "NETCUP",
        "speed": 622,
        "time": "2025-12-10 09:49:17"
    },
    {
        "colo": "Default",
        "ip": "2606:4700:440a:c652:37e4:22b7:3f50:a9de",
        "latency": 3,
        "line": "CT",
        "loss": 0,
        "node": "NETCUP",
        "speed": 448,
        "time": "2025-12-10 09:49:17"
    },
    {
        "colo": "Default",
        "ip": "2606:4700:9c6b:7a4d:b9ca:19a:a529:1e0",
        "latency": 3,
        "line": "CT",
        "loss": 0,
        "node": "NETCUP",
        "speed": 392,
        "time": "2025-12-10 09:49:17"
    },
    {
        "colo": "Default",
        "ip": "2606:4700:440a:1f16:ef42:9875:67b7:6289",
        "latency": 5,
        "line": "CT",
        "loss": 0,
        "node": "NETCUP",
        "speed": 373,
        "time": "2025-12-10 09:49:17"
    },
    {
        "colo": "Default",
        "ip": "2606:4700:3027:8c48:d109:4ab1:83cb:612c",
        "latency": 3,
        "line": "CT",
        "loss": 0,
        "node": "NETCUP",
        "speed": 361,
        "time": "2025-12-10 09:49:17"
    },
    {
        "colo": "Default",
        "ip": "2606:4700:9c6b:670f:1b66:50dd:7e31:d8e3",
        "latency": 3,
        "line": "CU",
        "loss": 0,
        "node": "NETCUP",
        "speed": 622,
        "time": "2025-12-10 09:49:17"
    },
    {
        "colo": "Default",
        "ip": "2606:4700:440a:c652:37e4:22b7:3f50:a9de",
        "latency": 3,
        "line": "CU",
        "loss": 0,
        "node": "NETCUP",
        "speed": 448,
        "time": "2025-12-10 09:49:17"
    },
    {
        "colo": "Default",
        "ip": "2606:4700:9c6b:7a4d:b9ca:19a:a529:1e0",
        "latency": 3,
        "line": "CU",
        "loss": 0,
        "node": "NETCUP",
        "speed": 392,
        "time": "2025-12-10 09:49:17"
    },
    {
        "colo": "Default",
        "ip": "2606:4700:440a:1f16:ef42:9875:67b7:6289",
        "latency": 5,
        "line": "CU",
        "loss": 0,
        "node": "NETCUP",
        "speed": 373,
        "time": "2025-12-10 09:49:17"
    },
    {
        "colo": "Default",
        "ip": "2606:4700:3027:8c48:d109:4ab1:83cb:612c",
        "latency": 3,
        "line": "CU",
        "loss": 0,
        "node": "NETCUP",
        "speed": 361,
        "time": "2025-12-10 09:49:17"
    }
]