[
    {
        "colo": "Default",
        "ip": "2606:4700:3035:8b25:a34c:80c5:a243:d8d2",
        "latency": 3,
        "line": "CM",
        "loss": 0,
        "node": "NETCUP",
        "speed": 601,
        "time": "2026-04-09 00:39:18"
    },
    {
        "colo": "Default",
        "ip": "2606:4700:3035:9a67:c43a:d097:1f2:2cb0",
        "latency": 13,
        "line": "CM",
        "loss": 0,
        "node": "NETCUP",
        "speed": 583,
        "time": "2026-04-09 00:39:18"
    },
    {
        "colo": "Default",
        "ip": "2606:4700:8caf:de91:72bd:cd2e:383b:a70c",
        "latency": 3,
        "line": "CM",
        "loss": 0,
        "node": "NETCUP",
        "speed": 518,
        "time": "2026-04-09 00:39:18"
    },
    {
        "colo": "Default",
        "ip": "2606:4700:300a:4afc:b859:46f0:6eb8:4aac",
        "latency": 3,
        "line": "CM",
        "loss": 0,
        "node": "NETCUP",
        "speed": 404,
        "time": "2026-04-09 00:39:18"
    },
    {
        "colo": "Default",
        "ip": "2606:4700:9b0d:5958:1724:c872:57c1:1ea2",
        "latency": 3,
        "line": "CM",
        "loss": 0,
        "node": "NETCUP",
        "speed": 316,
        "time": "2026-04-09 00:39:18"
    },
    {
        "colo": "Default",
        "ip": "2606:4700:3035:8b25:a34c:80c5:a243:d8d2",
        "latency": 3,
        "line": "CT",
        "loss": 0,
        "node": "NETCUP",
        "speed": 601,
        "time": "2026-04-09 00:39:18"
    },
    {
        "colo": "Default",
        "ip": "2606:4700:3035:9a67:c43a:d097:1f2:2cb0",
        "latency": 13,
        "line": "CT",
        "loss": 0,
        "node": "NETCUP",
        "speed": 583,
        "time": "2026-04-09 00:39:18"
    },
    {
        "colo": "Default",
        "ip": "2606:4700:8caf:de91:72bd:cd2e:383b:a70c",
        "latency": 3,
        "line": "CT",
        "loss": 0,
        "node": "NETCUP",
        "speed": 518,
        "time": "2026-04-09 00:39:18"
    },
    {
        "colo": "Default",
        "ip": "2606:4700:300a:4afc:b859:46f0:6eb8:4aac",
        "latency": 3,
        "line": "CT",
        "loss": 0,
        "node": "NETCUP",
        "speed": 404,
        "time": "2026-04-09 00:39:18"
    },
    {
        "colo": "Default",
        "ip": "2606:4700:9b0d:5958:1724:c872:57c1:1ea2",
        "latency": 3,
        "line": "CT",
        "loss": 0,
        "node": "NETCUP",
        "speed": 316,
        "time": "2026-04-09 00:39:18"
    },
    {
        "colo": "Default",
        "ip": "2606:4700:3035:8b25:a34c:80c5:a243:d8d2",
        "latency": 3,
        "line": "CU",
        "loss": 0,
        "node": "NETCUP",
        "speed": 601,
        "time": "2026-04-09 00:39:18"
    },
    {
        "colo": "Default",
        "ip": "2606:4700:3035:9a67:c43a:d097:1f2:2cb0",
        "latency": 13,
        "line": "CU",
        "loss": 0,
        "node": "NETCUP",
        "speed": 583,
        "time": "2026-04-09 00:39:18"
    },
    {
        "colo": "Default",
        "ip": "2606:4700:8caf:de91:72bd:cd2e:383b:a70c",
        "latency": 3,
        "line": "CU",
        "loss": 0,
        "node": "NETCUP",
        "speed": 518,
        "time": "2026-04-09 00:39:18"
    },
    {
        "colo": "Default",
        "ip": "2606:4700:300a:4afc:b859:46f0:6eb8:4aac",
        "latency": 3,
        "line": "CU",
        "loss": 0,
        "node": "NETCUP",
        "speed": 404,
        "time": "2026-04-09 00:39:18"
    },
    {
        "colo": "Default",
        "ip": "2606:4700:9b0d:5958:1724:c872:57c1:1ea2",
        "latency": 3,
        "line": "CU",
        "loss": 0,
        "node": "NETCUP",
        "speed": 316,
        "time": "2026-04-09 00:39:18"
    }
]