[
    {
        "colo": "Default",
        "ip": "2606:4700:839f:7db8:c4ee:b5e9:b8ea:eafc",
        "latency": 3,
        "line": "CM",
        "loss": 0,
        "node": "NETCUP",
        "speed": 565,
        "time": "2025-08-20 03:29:52"
    },
    {
        "colo": "Default",
        "ip": "2606:4700:8395:f92a:c1a8:c470:b18e:6b1",
        "latency": 3,
        "line": "CM",
        "loss": 0,
        "node": "NETCUP",
        "speed": 441,
        "time": "2025-08-20 03:29:52"
    },
    {
        "colo": "Default",
        "ip": "2606:4700:135:b9f1:593e:aa01:8b69:f295",
        "latency": 4,
        "line": "CM",
        "loss": 0,
        "node": "NETCUP",
        "speed": 437,
        "time": "2025-08-20 03:29:52"
    },
    {
        "colo": "Default",
        "ip": "2606:4700:839f:f0ce:b88b:b40e:66b:bbb5",
        "latency": 3,
        "line": "CM",
        "loss": 0,
        "node": "NETCUP",
        "speed": 427,
        "time": "2025-08-20 03:29:52"
    },
    {
        "colo": "Default",
        "ip": "2606:4700:9b0b:5021:118a:ab42:5c8b:5605",
        "latency": 3,
        "line": "CM",
        "loss": 0,
        "node": "NETCUP",
        "speed": 307,
        "time": "2025-08-20 03:29:52"
    },
    {
        "colo": "Default",
        "ip": "2606:4700:839f:7db8:c4ee:b5e9:b8ea:eafc",
        "latency": 3,
        "line": "CT",
        "loss": 0,
        "node": "NETCUP",
        "speed": 565,
        "time": "2025-08-20 03:29:52"
    },
    {
        "colo": "Default",
        "ip": "2606:4700:8395:f92a:c1a8:c470:b18e:6b1",
        "latency": 3,
        "line": "CT",
        "loss": 0,
        "node": "NETCUP",
        "speed": 441,
        "time": "2025-08-20 03:29:52"
    },
    {
        "colo": "Default",
        "ip": "2606:4700:135:b9f1:593e:aa01:8b69:f295",
        "latency": 4,
        "line": "CT",
        "loss": 0,
        "node": "NETCUP",
        "speed": 437,
        "time": "2025-08-20 03:29:52"
    },
    {
        "colo": "Default",
        "ip": "2606:4700:839f:f0ce:b88b:b40e:66b:bbb5",
        "latency": 3,
        "line": "CT",
        "loss": 0,
        "node": "NETCUP",
        "speed": 427,
        "time": "2025-08-20 03:29:52"
    },
    {
        "colo": "Default",
        "ip": "2606:4700:9b0b:5021:118a:ab42:5c8b:5605",
        "latency": 3,
        "line": "CT",
        "loss": 0,
        "node": "NETCUP",
        "speed": 307,
        "time": "2025-08-20 03:29:52"
    },
    {
        "colo": "Default",
        "ip": "2606:4700:839f:7db8:c4ee:b5e9:b8ea:eafc",
        "latency": 3,
        "line": "CU",
        "loss": 0,
        "node": "NETCUP",
        "speed": 565,
        "time": "2025-08-20 03:29:52"
    },
    {
        "colo": "Default",
        "ip": "2606:4700:8395:f92a:c1a8:c470:b18e:6b1",
        "latency": 3,
        "line": "CU",
        "loss": 0,
        "node": "NETCUP",
        "speed": 441,
        "time": "2025-08-20 03:29:52"
    },
    {
        "colo": "Default",
        "ip": "2606:4700:135:b9f1:593e:aa01:8b69:f295",
        "latency": 4,
        "line": "CU",
        "loss": 0,
        "node": "NETCUP",
        "speed": 437,
        "time": "2025-08-20 03:29:52"
    },
    {
        "colo": "Default",
        "ip": "2606:4700:839f:f0ce:b88b:b40e:66b:bbb5",
        "latency": 3,
        "line": "CU",
        "loss": 0,
        "node": "NETCUP",
        "speed": 427,
        "time": "2025-08-20 03:29:52"
    },
    {
        "colo": "Default",
        "ip": "2606:4700:9b0b:5021:118a:ab42:5c8b:5605",
        "latency": 3,
        "line": "CU",
        "loss": 0,
        "node": "NETCUP",
        "speed": 307,
        "time": "2025-08-20 03:29:52"
    }
]