[
    {
        "colo": "Default",
        "ip": "2606:4700:131:30f1:171:9b06:17de:a7c9",
        "latency": 13,
        "line": "CM",
        "loss": 0,
        "node": "NETCUP",
        "speed": 467,
        "time": "2025-10-16 10:49:48"
    },
    {
        "colo": "Default",
        "ip": "2606:4700:23:b3c3:de44:8c68:4d5c:29b3",
        "latency": 4,
        "line": "CM",
        "loss": 0,
        "node": "NETCUP",
        "speed": 423,
        "time": "2025-10-16 10:49:48"
    },
    {
        "colo": "Default",
        "ip": "2606:4700:23:eb54:3ec9:4236:1f57:c932",
        "latency": 4,
        "line": "CM",
        "loss": 0,
        "node": "NETCUP",
        "speed": 393,
        "time": "2025-10-16 10:49:48"
    },
    {
        "colo": "Default",
        "ip": "2606:4700:131:1a6c:8315:ada6:ede2:c1df",
        "latency": 4,
        "line": "CM",
        "loss": 0,
        "node": "NETCUP",
        "speed": 381,
        "time": "2025-10-16 10:49:48"
    },
    {
        "colo": "Default",
        "ip": "2606:4700:99ef:f5a8:ce00:4d33:d7e2:4094",
        "latency": 6,
        "line": "CM",
        "loss": 0,
        "node": "NETCUP",
        "speed": 367,
        "time": "2025-10-16 10:49:48"
    },
    {
        "colo": "Default",
        "ip": "2606:4700:131:30f1:171:9b06:17de:a7c9",
        "latency": 13,
        "line": "CT",
        "loss": 0,
        "node": "NETCUP",
        "speed": 467,
        "time": "2025-10-16 10:49:48"
    },
    {
        "colo": "Default",
        "ip": "2606:4700:23:b3c3:de44:8c68:4d5c:29b3",
        "latency": 4,
        "line": "CT",
        "loss": 0,
        "node": "NETCUP",
        "speed": 423,
        "time": "2025-10-16 10:49:48"
    },
    {
        "colo": "Default",
        "ip": "2606:4700:23:eb54:3ec9:4236:1f57:c932",
        "latency": 4,
        "line": "CT",
        "loss": 0,
        "node": "NETCUP",
        "speed": 393,
        "time": "2025-10-16 10:49:48"
    },
    {
        "colo": "Default",
        "ip": "2606:4700:131:1a6c:8315:ada6:ede2:c1df",
        "latency": 4,
        "line": "CT",
        "loss": 0,
        "node": "NETCUP",
        "speed": 381,
        "time": "2025-10-16 10:49:48"
    },
    {
        "colo": "Default",
        "ip": "2606:4700:99ef:f5a8:ce00:4d33:d7e2:4094",
        "latency": 6,
        "line": "CT",
        "loss": 0,
        "node": "NETCUP",
        "speed": 367,
        "time": "2025-10-16 10:49:48"
    },
    {
        "colo": "Default",
        "ip": "2606:4700:131:30f1:171:9b06:17de:a7c9",
        "latency": 13,
        "line": "CU",
        "loss": 0,
        "node": "NETCUP",
        "speed": 467,
        "time": "2025-10-16 10:49:48"
    },
    {
        "colo": "Default",
        "ip": "2606:4700:23:b3c3:de44:8c68:4d5c:29b3",
        "latency": 4,
        "line": "CU",
        "loss": 0,
        "node": "NETCUP",
        "speed": 423,
        "time": "2025-10-16 10:49:48"
    },
    {
        "colo": "Default",
        "ip": "2606:4700:23:eb54:3ec9:4236:1f57:c932",
        "latency": 4,
        "line": "CU",
        "loss": 0,
        "node": "NETCUP",
        "speed": 393,
        "time": "2025-10-16 10:49:48"
    },
    {
        "colo": "Default",
        "ip": "2606:4700:131:1a6c:8315:ada6:ede2:c1df",
        "latency": 4,
        "line": "CU",
        "loss": 0,
        "node": "NETCUP",
        "speed": 381,
        "time": "2025-10-16 10:49:48"
    },
    {
        "colo": "Default",
        "ip": "2606:4700:99ef:f5a8:ce00:4d33:d7e2:4094",
        "latency": 6,
        "line": "CU",
        "loss": 0,
        "node": "NETCUP",
        "speed": 367,
        "time": "2025-10-16 10:49:48"
    }
]