[
    {
        "colo": "Default",
        "ip": "2606:4700:9aed:4bd0:d550:909c:d42e:68cf",
        "latency": 3,
        "line": "CM",
        "loss": 0,
        "node": "NETCUP",
        "speed": 576,
        "time": "2025-08-25 06:19:47"
    },
    {
        "colo": "Default",
        "ip": "2606:4700:83b6:b71f:36b2:b2af:c1df:b704",
        "latency": 159,
        "line": "CM",
        "loss": 0,
        "node": "NETCUP",
        "speed": 459,
        "time": "2025-08-25 06:19:48"
    },
    {
        "colo": "Default",
        "ip": "2606:4700:3001:1895:8550:7661:ff51:4b92",
        "latency": 4,
        "line": "CM",
        "loss": 0,
        "node": "NETCUP",
        "speed": 383,
        "time": "2025-08-25 06:19:48"
    },
    {
        "colo": "Default",
        "ip": "2606:4700:8ca7:cbe:e463:ca3a:eab4:cc53",
        "latency": 3,
        "line": "CM",
        "loss": 0,
        "node": "NETCUP",
        "speed": 380,
        "time": "2025-08-25 06:19:48"
    },
    {
        "colo": "Default",
        "ip": "2606:4700:3001:c7bc:1b89:230f:575a:a88a",
        "latency": 3,
        "line": "CM",
        "loss": 0,
        "node": "NETCUP",
        "speed": 380,
        "time": "2025-08-25 06:19:47"
    },
    {
        "colo": "Default",
        "ip": "2606:4700:9aed:4bd0:d550:909c:d42e:68cf",
        "latency": 3,
        "line": "CT",
        "loss": 0,
        "node": "NETCUP",
        "speed": 576,
        "time": "2025-08-25 06:19:47"
    },
    {
        "colo": "Default",
        "ip": "2606:4700:83b6:b71f:36b2:b2af:c1df:b704",
        "latency": 159,
        "line": "CT",
        "loss": 0,
        "node": "NETCUP",
        "speed": 459,
        "time": "2025-08-25 06:19:48"
    },
    {
        "colo": "Default",
        "ip": "2606:4700:3001:1895:8550:7661:ff51:4b92",
        "latency": 4,
        "line": "CT",
        "loss": 0,
        "node": "NETCUP",
        "speed": 383,
        "time": "2025-08-25 06:19:48"
    },
    {
        "colo": "Default",
        "ip": "2606:4700:8ca7:cbe:e463:ca3a:eab4:cc53",
        "latency": 3,
        "line": "CT",
        "loss": 0,
        "node": "NETCUP",
        "speed": 380,
        "time": "2025-08-25 06:19:48"
    },
    {
        "colo": "Default",
        "ip": "2606:4700:3001:c7bc:1b89:230f:575a:a88a",
        "latency": 3,
        "line": "CT",
        "loss": 0,
        "node": "NETCUP",
        "speed": 380,
        "time": "2025-08-25 06:19:47"
    },
    {
        "colo": "Default",
        "ip": "2606:4700:9aed:4bd0:d550:909c:d42e:68cf",
        "latency": 3,
        "line": "CU",
        "loss": 0,
        "node": "NETCUP",
        "speed": 576,
        "time": "2025-08-25 06:19:47"
    },
    {
        "colo": "Default",
        "ip": "2606:4700:83b6:b71f:36b2:b2af:c1df:b704",
        "latency": 159,
        "line": "CU",
        "loss": 0,
        "node": "NETCUP",
        "speed": 459,
        "time": "2025-08-25 06:19:48"
    },
    {
        "colo": "Default",
        "ip": "2606:4700:3001:1895:8550:7661:ff51:4b92",
        "latency": 4,
        "line": "CU",
        "loss": 0,
        "node": "NETCUP",
        "speed": 383,
        "time": "2025-08-25 06:19:48"
    },
    {
        "colo": "Default",
        "ip": "2606:4700:8ca7:cbe:e463:ca3a:eab4:cc53",
        "latency": 3,
        "line": "CU",
        "loss": 0,
        "node": "NETCUP",
        "speed": 380,
        "time": "2025-08-25 06:19:48"
    },
    {
        "colo": "Default",
        "ip": "2606:4700:3001:c7bc:1b89:230f:575a:a88a",
        "latency": 3,
        "line": "CU",
        "loss": 0,
        "node": "NETCUP",
        "speed": 380,
        "time": "2025-08-25 06:19:47"
    }
]