[
    {
        "colo": "Default",
        "ip": "2606:4700:9a92:b3af:6b6:ed6d:54f9:f418",
        "latency": 4,
        "line": "CM",
        "loss": 0,
        "node": "NETCUP",
        "speed": 392,
        "time": "2025-10-18 10:59:51"
    },
    {
        "colo": "Default",
        "ip": "2606:4700:9a95:d3d7:3d7c:3ad3:1104:623",
        "latency": 3,
        "line": "CM",
        "loss": 0,
        "node": "NETCUP",
        "speed": 384,
        "time": "2025-10-18 11:09:48"
    },
    {
        "colo": "Default",
        "ip": "2606:4700:90cb:d313:81f8:e5f9:229d:3e24",
        "latency": 3,
        "line": "CM",
        "loss": 0,
        "node": "NETCUP",
        "speed": 383,
        "time": "2025-10-18 11:09:48"
    },
    {
        "colo": "Default",
        "ip": "2606:4700:90da:215d:54b6:16d2:6444:939",
        "latency": 3,
        "line": "CM",
        "loss": 0,
        "node": "NETCUP",
        "speed": 368,
        "time": "2025-10-18 11:09:48"
    },
    {
        "colo": "Default",
        "ip": "2606:4700:9a95:4d0f:8118:518:9fc6:d1d7",
        "latency": 3,
        "line": "CM",
        "loss": 0,
        "node": "NETCUP",
        "speed": 340,
        "time": "2025-10-18 11:09:48"
    },
    {
        "colo": "Default",
        "ip": "2606:4700:9a92:b3af:6b6:ed6d:54f9:f418",
        "latency": 4,
        "line": "CT",
        "loss": 0,
        "node": "NETCUP",
        "speed": 392,
        "time": "2025-10-18 10:59:51"
    },
    {
        "colo": "Default",
        "ip": "2606:4700:9a95:d3d7:3d7c:3ad3:1104:623",
        "latency": 3,
        "line": "CT",
        "loss": 0,
        "node": "NETCUP",
        "speed": 384,
        "time": "2025-10-18 11:09:48"
    },
    {
        "colo": "Default",
        "ip": "2606:4700:90cb:d313:81f8:e5f9:229d:3e24",
        "latency": 3,
        "line": "CT",
        "loss": 0,
        "node": "NETCUP",
        "speed": 383,
        "time": "2025-10-18 11:09:48"
    },
    {
        "colo": "Default",
        "ip": "2606:4700:90da:215d:54b6:16d2:6444:939",
        "latency": 3,
        "line": "CT",
        "loss": 0,
        "node": "NETCUP",
        "speed": 368,
        "time": "2025-10-18 11:09:48"
    },
    {
        "colo": "Default",
        "ip": "2606:4700:9a95:4d0f:8118:518:9fc6:d1d7",
        "latency": 3,
        "line": "CT",
        "loss": 0,
        "node": "NETCUP",
        "speed": 340,
        "time": "2025-10-18 11:09:48"
    },
    {
        "colo": "Default",
        "ip": "2606:4700:9a92:b3af:6b6:ed6d:54f9:f418",
        "latency": 4,
        "line": "CU",
        "loss": 0,
        "node": "NETCUP",
        "speed": 392,
        "time": "2025-10-18 10:59:51"
    },
    {
        "colo": "Default",
        "ip": "2606:4700:9a95:d3d7:3d7c:3ad3:1104:623",
        "latency": 3,
        "line": "CU",
        "loss": 0,
        "node": "NETCUP",
        "speed": 384,
        "time": "2025-10-18 11:09:48"
    },
    {
        "colo": "Default",
        "ip": "2606:4700:90cb:d313:81f8:e5f9:229d:3e24",
        "latency": 3,
        "line": "CU",
        "loss": 0,
        "node": "NETCUP",
        "speed": 383,
        "time": "2025-10-18 11:09:48"
    },
    {
        "colo": "Default",
        "ip": "2606:4700:90da:215d:54b6:16d2:6444:939",
        "latency": 3,
        "line": "CU",
        "loss": 0,
        "node": "NETCUP",
        "speed": 368,
        "time": "2025-10-18 11:09:48"
    },
    {
        "colo": "Default",
        "ip": "2606:4700:9a95:4d0f:8118:518:9fc6:d1d7",
        "latency": 3,
        "line": "CU",
        "loss": 0,
        "node": "NETCUP",
        "speed": 340,
        "time": "2025-10-18 11:09:48"
    }
]