[
    {
        "colo": "Default",
        "ip": "2606:4700:8ca7:2288:db4a:2009:370b:13c8",
        "latency": 3,
        "line": "CM",
        "loss": 0,
        "node": "NETCUP",
        "speed": 611,
        "time": "2026-04-19 05:19:17"
    },
    {
        "colo": "Default",
        "ip": "2606:4700:8ca7:577:90be:e2f9:9914:c590",
        "latency": 3,
        "line": "CM",
        "loss": 0,
        "node": "NETCUP",
        "speed": 555,
        "time": "2026-04-19 05:19:17"
    },
    {
        "colo": "Default",
        "ip": "2606:4700:3017:4490:4aa1:4ac1:bd7b:b776",
        "latency": 12,
        "line": "CM",
        "loss": 0,
        "node": "NETCUP",
        "speed": 338,
        "time": "2026-04-19 05:19:17"
    },
    {
        "colo": "Default",
        "ip": "2606:4700:9ade:b518:abea:4554:b441:5009",
        "latency": 3,
        "line": "CM",
        "loss": 0,
        "node": "NETCUP",
        "speed": 317,
        "time": "2026-04-19 05:19:17"
    },
    {
        "colo": "Default",
        "ip": "2606:4700:3017:db5c:900f:733:d7ed:ab43",
        "latency": 3,
        "line": "CM",
        "loss": 0,
        "node": "NETCUP",
        "speed": 309,
        "time": "2026-04-19 05:19:17"
    },
    {
        "colo": "Default",
        "ip": "2606:4700:8ca7:2288:db4a:2009:370b:13c8",
        "latency": 3,
        "line": "CT",
        "loss": 0,
        "node": "NETCUP",
        "speed": 611,
        "time": "2026-04-19 05:19:17"
    },
    {
        "colo": "Default",
        "ip": "2606:4700:8ca7:577:90be:e2f9:9914:c590",
        "latency": 3,
        "line": "CT",
        "loss": 0,
        "node": "NETCUP",
        "speed": 555,
        "time": "2026-04-19 05:19:17"
    },
    {
        "colo": "Default",
        "ip": "2606:4700:3017:4490:4aa1:4ac1:bd7b:b776",
        "latency": 12,
        "line": "CT",
        "loss": 0,
        "node": "NETCUP",
        "speed": 338,
        "time": "2026-04-19 05:19:17"
    },
    {
        "colo": "Default",
        "ip": "2606:4700:9ade:b518:abea:4554:b441:5009",
        "latency": 3,
        "line": "CT",
        "loss": 0,
        "node": "NETCUP",
        "speed": 317,
        "time": "2026-04-19 05:19:17"
    },
    {
        "colo": "Default",
        "ip": "2606:4700:3017:db5c:900f:733:d7ed:ab43",
        "latency": 3,
        "line": "CT",
        "loss": 0,
        "node": "NETCUP",
        "speed": 309,
        "time": "2026-04-19 05:19:17"
    },
    {
        "colo": "Default",
        "ip": "2606:4700:8ca7:2288:db4a:2009:370b:13c8",
        "latency": 3,
        "line": "CU",
        "loss": 0,
        "node": "NETCUP",
        "speed": 611,
        "time": "2026-04-19 05:19:17"
    },
    {
        "colo": "Default",
        "ip": "2606:4700:8ca7:577:90be:e2f9:9914:c590",
        "latency": 3,
        "line": "CU",
        "loss": 0,
        "node": "NETCUP",
        "speed": 555,
        "time": "2026-04-19 05:19:17"
    },
    {
        "colo": "Default",
        "ip": "2606:4700:3017:4490:4aa1:4ac1:bd7b:b776",
        "latency": 12,
        "line": "CU",
        "loss": 0,
        "node": "NETCUP",
        "speed": 338,
        "time": "2026-04-19 05:19:17"
    },
    {
        "colo": "Default",
        "ip": "2606:4700:9ade:b518:abea:4554:b441:5009",
        "latency": 3,
        "line": "CU",
        "loss": 0,
        "node": "NETCUP",
        "speed": 317,
        "time": "2026-04-19 05:19:17"
    },
    {
        "colo": "Default",
        "ip": "2606:4700:3017:db5c:900f:733:d7ed:ab43",
        "latency": 3,
        "line": "CU",
        "loss": 0,
        "node": "NETCUP",
        "speed": 309,
        "time": "2026-04-19 05:19:17"
    }
]