[
    {
        "colo": "Default",
        "ip": "2606:4700:8dda:e2c8:9640:137b:8fb0:67c7",
        "latency": 3,
        "line": "CM",
        "loss": 0,
        "node": "NETCUP",
        "speed": 619,
        "time": "2026-05-10 05:19:18"
    },
    {
        "colo": "Default",
        "ip": "2606:4700:99eb:d0c1:37d:5089:a55f:6caa",
        "latency": 3,
        "line": "CM",
        "loss": 0,
        "node": "NETCUP",
        "speed": 617,
        "time": "2026-05-10 05:19:18"
    },
    {
        "colo": "Default",
        "ip": "2606:4700:8d99:440f:f203:5499:23cd:a855",
        "latency": 3,
        "line": "CM",
        "loss": 0,
        "node": "NETCUP",
        "speed": 613,
        "time": "2026-05-10 05:19:18"
    },
    {
        "colo": "Default",
        "ip": "2606:4700:8d99:f079:3ddd:2396:e583:1afb",
        "latency": 3,
        "line": "CM",
        "loss": 0,
        "node": "NETCUP",
        "speed": 612,
        "time": "2026-05-10 05:19:18"
    },
    {
        "colo": "Default",
        "ip": "2606:4700:3020:c584:4f63:7cfa:55ab:1adf",
        "latency": 3,
        "line": "CM",
        "loss": 0,
        "node": "NETCUP",
        "speed": 317,
        "time": "2026-05-10 05:19:18"
    },
    {
        "colo": "Default",
        "ip": "2606:4700:8dda:e2c8:9640:137b:8fb0:67c7",
        "latency": 3,
        "line": "CT",
        "loss": 0,
        "node": "NETCUP",
        "speed": 619,
        "time": "2026-05-10 05:19:18"
    },
    {
        "colo": "Default",
        "ip": "2606:4700:99eb:d0c1:37d:5089:a55f:6caa",
        "latency": 3,
        "line": "CT",
        "loss": 0,
        "node": "NETCUP",
        "speed": 617,
        "time": "2026-05-10 05:19:18"
    },
    {
        "colo": "Default",
        "ip": "2606:4700:8d99:440f:f203:5499:23cd:a855",
        "latency": 3,
        "line": "CT",
        "loss": 0,
        "node": "NETCUP",
        "speed": 613,
        "time": "2026-05-10 05:19:18"
    },
    {
        "colo": "Default",
        "ip": "2606:4700:8d99:f079:3ddd:2396:e583:1afb",
        "latency": 3,
        "line": "CT",
        "loss": 0,
        "node": "NETCUP",
        "speed": 612,
        "time": "2026-05-10 05:19:18"
    },
    {
        "colo": "Default",
        "ip": "2606:4700:3020:c584:4f63:7cfa:55ab:1adf",
        "latency": 3,
        "line": "CT",
        "loss": 0,
        "node": "NETCUP",
        "speed": 317,
        "time": "2026-05-10 05:19:18"
    },
    {
        "colo": "Default",
        "ip": "2606:4700:8dda:e2c8:9640:137b:8fb0:67c7",
        "latency": 3,
        "line": "CU",
        "loss": 0,
        "node": "NETCUP",
        "speed": 619,
        "time": "2026-05-10 05:19:18"
    },
    {
        "colo": "Default",
        "ip": "2606:4700:99eb:d0c1:37d:5089:a55f:6caa",
        "latency": 3,
        "line": "CU",
        "loss": 0,
        "node": "NETCUP",
        "speed": 617,
        "time": "2026-05-10 05:19:18"
    },
    {
        "colo": "Default",
        "ip": "2606:4700:8d99:440f:f203:5499:23cd:a855",
        "latency": 3,
        "line": "CU",
        "loss": 0,
        "node": "NETCUP",
        "speed": 613,
        "time": "2026-05-10 05:19:18"
    },
    {
        "colo": "Default",
        "ip": "2606:4700:8d99:f079:3ddd:2396:e583:1afb",
        "latency": 3,
        "line": "CU",
        "loss": 0,
        "node": "NETCUP",
        "speed": 612,
        "time": "2026-05-10 05:19:18"
    },
    {
        "colo": "Default",
        "ip": "2606:4700:3020:c584:4f63:7cfa:55ab:1adf",
        "latency": 3,
        "line": "CU",
        "loss": 0,
        "node": "NETCUP",
        "speed": 317,
        "time": "2026-05-10 05:19:18"
    }
]