[
    {
        "colo": "Default",
        "ip": "2606:4700:9768:39f9:6f8:ad82:e6e9:6eba",
        "latency": 4,
        "line": "CM",
        "loss": 0,
        "node": "NETCUP",
        "speed": 622,
        "time": "2025-06-08 09:45:53"
    },
    {
        "colo": "Default",
        "ip": "2606:4700:26:8ab2:2edd:6cb4:cd25:4542",
        "latency": 3,
        "line": "CM",
        "loss": 0,
        "node": "NETCUP",
        "speed": 598,
        "time": "2025-06-08 09:45:53"
    },
    {
        "colo": "Default",
        "ip": "2606:4700:9768:130b:7bf3:9cbe:f6b1:a094",
        "latency": 4,
        "line": "CM",
        "loss": 0,
        "node": "NETCUP",
        "speed": 439,
        "time": "2025-06-08 09:45:53"
    },
    {
        "colo": "Default",
        "ip": "2606:4700:91bb:15a2:dea3:d8a9:9a8:a120",
        "latency": 3,
        "line": "CM",
        "loss": 0,
        "node": "NETCUP",
        "speed": 439,
        "time": "2025-06-08 09:45:53"
    },
    {
        "colo": "Default",
        "ip": "2606:4700:8d9a:e4d8:cf41:97b2:3ecf:6c09",
        "latency": 3,
        "line": "CM",
        "loss": 0,
        "node": "NETCUP",
        "speed": 392,
        "time": "2025-06-08 09:45:53"
    },
    {
        "colo": "Default",
        "ip": "2606:4700:9768:39f9:6f8:ad82:e6e9:6eba",
        "latency": 4,
        "line": "CT",
        "loss": 0,
        "node": "NETCUP",
        "speed": 622,
        "time": "2025-06-08 09:45:53"
    },
    {
        "colo": "Default",
        "ip": "2606:4700:26:8ab2:2edd:6cb4:cd25:4542",
        "latency": 3,
        "line": "CT",
        "loss": 0,
        "node": "NETCUP",
        "speed": 598,
        "time": "2025-06-08 09:45:53"
    },
    {
        "colo": "Default",
        "ip": "2606:4700:9768:130b:7bf3:9cbe:f6b1:a094",
        "latency": 4,
        "line": "CT",
        "loss": 0,
        "node": "NETCUP",
        "speed": 439,
        "time": "2025-06-08 09:45:53"
    },
    {
        "colo": "Default",
        "ip": "2606:4700:91bb:15a2:dea3:d8a9:9a8:a120",
        "latency": 3,
        "line": "CT",
        "loss": 0,
        "node": "NETCUP",
        "speed": 439,
        "time": "2025-06-08 09:45:53"
    },
    {
        "colo": "Default",
        "ip": "2606:4700:8d9a:e4d8:cf41:97b2:3ecf:6c09",
        "latency": 3,
        "line": "CT",
        "loss": 0,
        "node": "NETCUP",
        "speed": 392,
        "time": "2025-06-08 09:45:53"
    },
    {
        "colo": "Default",
        "ip": "2606:4700:9768:39f9:6f8:ad82:e6e9:6eba",
        "latency": 4,
        "line": "CU",
        "loss": 0,
        "node": "NETCUP",
        "speed": 622,
        "time": "2025-06-08 09:45:53"
    },
    {
        "colo": "Default",
        "ip": "2606:4700:26:8ab2:2edd:6cb4:cd25:4542",
        "latency": 3,
        "line": "CU",
        "loss": 0,
        "node": "NETCUP",
        "speed": 598,
        "time": "2025-06-08 09:45:53"
    },
    {
        "colo": "Default",
        "ip": "2606:4700:9768:130b:7bf3:9cbe:f6b1:a094",
        "latency": 4,
        "line": "CU",
        "loss": 0,
        "node": "NETCUP",
        "speed": 439,
        "time": "2025-06-08 09:45:53"
    },
    {
        "colo": "Default",
        "ip": "2606:4700:91bb:15a2:dea3:d8a9:9a8:a120",
        "latency": 3,
        "line": "CU",
        "loss": 0,
        "node": "NETCUP",
        "speed": 439,
        "time": "2025-06-08 09:45:53"
    },
    {
        "colo": "Default",
        "ip": "2606:4700:8d9a:e4d8:cf41:97b2:3ecf:6c09",
        "latency": 3,
        "line": "CU",
        "loss": 0,
        "node": "NETCUP",
        "speed": 392,
        "time": "2025-06-08 09:45:53"
    }
]