[
    {
        "colo": "Default",
        "ip": "2606:4700:131:cf26:d06e:b039:e117:fbaa",
        "latency": 1,
        "line": "CM",
        "loss": 10,
        "node": "PROHOSTING24",
        "speed": 611,
        "time": "2026-04-01 19:49:16"
    },
    {
        "colo": "Default",
        "ip": "2606:4700:131:e2fd:5547:3275:9f15:f562",
        "latency": 1,
        "line": "CM",
        "loss": 20,
        "node": "PROHOSTING24",
        "speed": 559,
        "time": "2026-04-01 19:49:16"
    },
    {
        "colo": "Default",
        "ip": "2606:4700:8396:2fd8:9e0b:67fa:b7dd:6dc5",
        "latency": 1,
        "line": "CM",
        "loss": 10,
        "node": "PROHOSTING24",
        "speed": 365,
        "time": "2026-04-01 19:49:16"
    },
    {
        "colo": "Default",
        "ip": "2606:4700:1c:cac1:77fc:b9e6:a1dd:4ce6",
        "latency": 1,
        "line": "CM",
        "loss": 20,
        "node": "PROHOSTING24",
        "speed": 323,
        "time": "2026-04-01 19:49:16"
    },
    {
        "colo": "Default",
        "ip": "2606:4700:90cb:3d11:bfdf:6120:d755:26e",
        "latency": 1,
        "line": "CM",
        "loss": 10,
        "node": "PROHOSTING24",
        "speed": 316,
        "time": "2026-04-01 19:49:16"
    },
    {
        "colo": "Default",
        "ip": "2606:4700:131:cf26:d06e:b039:e117:fbaa",
        "latency": 1,
        "line": "CT",
        "loss": 10,
        "node": "PROHOSTING24",
        "speed": 611,
        "time": "2026-04-01 19:49:16"
    },
    {
        "colo": "Default",
        "ip": "2606:4700:131:e2fd:5547:3275:9f15:f562",
        "latency": 1,
        "line": "CT",
        "loss": 20,
        "node": "PROHOSTING24",
        "speed": 559,
        "time": "2026-04-01 19:49:16"
    },
    {
        "colo": "Default",
        "ip": "2606:4700:8396:2fd8:9e0b:67fa:b7dd:6dc5",
        "latency": 1,
        "line": "CT",
        "loss": 10,
        "node": "PROHOSTING24",
        "speed": 365,
        "time": "2026-04-01 19:49:16"
    },
    {
        "colo": "Default",
        "ip": "2606:4700:1c:cac1:77fc:b9e6:a1dd:4ce6",
        "latency": 1,
        "line": "CT",
        "loss": 20,
        "node": "PROHOSTING24",
        "speed": 323,
        "time": "2026-04-01 19:49:16"
    },
    {
        "colo": "Default",
        "ip": "2606:4700:90cb:3d11:bfdf:6120:d755:26e",
        "latency": 1,
        "line": "CT",
        "loss": 10,
        "node": "PROHOSTING24",
        "speed": 316,
        "time": "2026-04-01 19:49:16"
    },
    {
        "colo": "Default",
        "ip": "2606:4700:131:cf26:d06e:b039:e117:fbaa",
        "latency": 1,
        "line": "CU",
        "loss": 10,
        "node": "PROHOSTING24",
        "speed": 611,
        "time": "2026-04-01 19:49:16"
    },
    {
        "colo": "Default",
        "ip": "2606:4700:131:e2fd:5547:3275:9f15:f562",
        "latency": 1,
        "line": "CU",
        "loss": 20,
        "node": "PROHOSTING24",
        "speed": 559,
        "time": "2026-04-01 19:49:16"
    },
    {
        "colo": "Default",
        "ip": "2606:4700:8396:2fd8:9e0b:67fa:b7dd:6dc5",
        "latency": 1,
        "line": "CU",
        "loss": 10,
        "node": "PROHOSTING24",
        "speed": 365,
        "time": "2026-04-01 19:49:16"
    },
    {
        "colo": "Default",
        "ip": "2606:4700:1c:cac1:77fc:b9e6:a1dd:4ce6",
        "latency": 1,
        "line": "CU",
        "loss": 20,
        "node": "PROHOSTING24",
        "speed": 323,
        "time": "2026-04-01 19:49:16"
    },
    {
        "colo": "Default",
        "ip": "2606:4700:90cb:3d11:bfdf:6120:d755:26e",
        "latency": 1,
        "line": "CU",
        "loss": 10,
        "node": "PROHOSTING24",
        "speed": 316,
        "time": "2026-04-01 19:49:16"
    }
]