[
    {
        "colo": "Default",
        "ip": "2606:4700:4408:c10a:6c42:4d1c:2186:1469",
        "latency": 0,
        "line": "CM",
        "loss": 0,
        "node": "PROHOSTING24",
        "speed": 388,
        "time": "2026-04-16 22:49:13"
    },
    {
        "colo": "Default",
        "ip": "2606:4700:9c64:99c:4d83:ef01:4d85:d29a",
        "latency": 1,
        "line": "CM",
        "loss": 0,
        "node": "PROHOSTING24",
        "speed": 334,
        "time": "2026-04-16 22:49:13"
    },
    {
        "colo": "Default",
        "ip": "2606:4700:90ce:83d5:9ca8:4d7c:8073:ca67",
        "latency": 3,
        "line": "CM",
        "loss": 0,
        "node": "NETCUP",
        "speed": 331,
        "time": "2026-04-16 22:39:17"
    },
    {
        "colo": "Default",
        "ip": "2606:4700:90ce:fb34:fd90:ccc0:282b:d5bb",
        "latency": 3,
        "line": "CM",
        "loss": 0,
        "node": "NETCUP",
        "speed": 318,
        "time": "2026-04-16 22:39:17"
    },
    {
        "colo": "Default",
        "ip": "2606:4700:90cb:6ca:77d4:58b7:e35d:14d9",
        "latency": 3,
        "line": "CM",
        "loss": 0,
        "node": "NETCUP",
        "speed": 314,
        "time": "2026-04-16 22:39:17"
    },
    {
        "colo": "Default",
        "ip": "2606:4700:4408:c10a:6c42:4d1c:2186:1469",
        "latency": 0,
        "line": "CT",
        "loss": 0,
        "node": "PROHOSTING24",
        "speed": 388,
        "time": "2026-04-16 22:49:13"
    },
    {
        "colo": "Default",
        "ip": "2606:4700:9c64:99c:4d83:ef01:4d85:d29a",
        "latency": 1,
        "line": "CT",
        "loss": 0,
        "node": "PROHOSTING24",
        "speed": 334,
        "time": "2026-04-16 22:49:13"
    },
    {
        "colo": "Default",
        "ip": "2606:4700:90ce:83d5:9ca8:4d7c:8073:ca67",
        "latency": 3,
        "line": "CT",
        "loss": 0,
        "node": "NETCUP",
        "speed": 331,
        "time": "2026-04-16 22:39:17"
    },
    {
        "colo": "Default",
        "ip": "2606:4700:90ce:fb34:fd90:ccc0:282b:d5bb",
        "latency": 3,
        "line": "CT",
        "loss": 0,
        "node": "NETCUP",
        "speed": 318,
        "time": "2026-04-16 22:39:17"
    },
    {
        "colo": "Default",
        "ip": "2606:4700:90cb:6ca:77d4:58b7:e35d:14d9",
        "latency": 3,
        "line": "CT",
        "loss": 0,
        "node": "NETCUP",
        "speed": 314,
        "time": "2026-04-16 22:39:17"
    },
    {
        "colo": "Default",
        "ip": "2606:4700:4408:c10a:6c42:4d1c:2186:1469",
        "latency": 0,
        "line": "CU",
        "loss": 0,
        "node": "PROHOSTING24",
        "speed": 388,
        "time": "2026-04-16 22:49:13"
    },
    {
        "colo": "Default",
        "ip": "2606:4700:9c64:99c:4d83:ef01:4d85:d29a",
        "latency": 1,
        "line": "CU",
        "loss": 0,
        "node": "PROHOSTING24",
        "speed": 334,
        "time": "2026-04-16 22:49:13"
    },
    {
        "colo": "Default",
        "ip": "2606:4700:90ce:83d5:9ca8:4d7c:8073:ca67",
        "latency": 3,
        "line": "CU",
        "loss": 0,
        "node": "NETCUP",
        "speed": 331,
        "time": "2026-04-16 22:39:17"
    },
    {
        "colo": "Default",
        "ip": "2606:4700:90ce:fb34:fd90:ccc0:282b:d5bb",
        "latency": 3,
        "line": "CU",
        "loss": 0,
        "node": "NETCUP",
        "speed": 318,
        "time": "2026-04-16 22:39:17"
    },
    {
        "colo": "Default",
        "ip": "2606:4700:90cb:6ca:77d4:58b7:e35d:14d9",
        "latency": 3,
        "line": "CU",
        "loss": 0,
        "node": "NETCUP",
        "speed": 314,
        "time": "2026-04-16 22:39:17"
    }
]