[
    {
        "colo": "Default",
        "ip": "2606:4700:9648:a121:92dc:7691:45fa:952",
        "latency": 3,
        "line": "CM",
        "loss": 0,
        "node": "NETCUP",
        "speed": 622,
        "time": "2025-10-03 04:19:51"
    },
    {
        "colo": "Default",
        "ip": "2606:4700:d1:6140:d879:3ac1:7939:d8df",
        "latency": 4,
        "line": "CM",
        "loss": 0,
        "node": "NETCUP",
        "speed": 500,
        "time": "2025-10-03 04:19:51"
    },
    {
        "colo": "Default",
        "ip": "2606:4700:1a:1794:78b8:a3a9:fb71:fb6d",
        "latency": 3,
        "line": "CM",
        "loss": 0,
        "node": "NETCUP",
        "speed": 439,
        "time": "2025-10-03 04:19:51"
    },
    {
        "colo": "Default",
        "ip": "2606:4700:11:5aaf:536:69d8:7500:aae6",
        "latency": 4,
        "line": "CM",
        "loss": 0,
        "node": "NETCUP",
        "speed": 425,
        "time": "2025-10-03 04:19:51"
    },
    {
        "colo": "Default",
        "ip": "2606:4700:11:ac73:fe7b:36e4:cf0f:6721",
        "latency": 4,
        "line": "CM",
        "loss": 0,
        "node": "NETCUP",
        "speed": 406,
        "time": "2025-10-03 04:19:51"
    },
    {
        "colo": "Default",
        "ip": "2606:4700:9648:a121:92dc:7691:45fa:952",
        "latency": 3,
        "line": "CT",
        "loss": 0,
        "node": "NETCUP",
        "speed": 622,
        "time": "2025-10-03 04:19:51"
    },
    {
        "colo": "Default",
        "ip": "2606:4700:d1:6140:d879:3ac1:7939:d8df",
        "latency": 4,
        "line": "CT",
        "loss": 0,
        "node": "NETCUP",
        "speed": 500,
        "time": "2025-10-03 04:19:51"
    },
    {
        "colo": "Default",
        "ip": "2606:4700:1a:1794:78b8:a3a9:fb71:fb6d",
        "latency": 3,
        "line": "CT",
        "loss": 0,
        "node": "NETCUP",
        "speed": 439,
        "time": "2025-10-03 04:19:51"
    },
    {
        "colo": "Default",
        "ip": "2606:4700:11:5aaf:536:69d8:7500:aae6",
        "latency": 4,
        "line": "CT",
        "loss": 0,
        "node": "NETCUP",
        "speed": 425,
        "time": "2025-10-03 04:19:51"
    },
    {
        "colo": "Default",
        "ip": "2606:4700:11:ac73:fe7b:36e4:cf0f:6721",
        "latency": 4,
        "line": "CT",
        "loss": 0,
        "node": "NETCUP",
        "speed": 406,
        "time": "2025-10-03 04:19:51"
    },
    {
        "colo": "Default",
        "ip": "2606:4700:9648:a121:92dc:7691:45fa:952",
        "latency": 3,
        "line": "CU",
        "loss": 0,
        "node": "NETCUP",
        "speed": 622,
        "time": "2025-10-03 04:19:51"
    },
    {
        "colo": "Default",
        "ip": "2606:4700:d1:6140:d879:3ac1:7939:d8df",
        "latency": 4,
        "line": "CU",
        "loss": 0,
        "node": "NETCUP",
        "speed": 500,
        "time": "2025-10-03 04:19:51"
    },
    {
        "colo": "Default",
        "ip": "2606:4700:1a:1794:78b8:a3a9:fb71:fb6d",
        "latency": 3,
        "line": "CU",
        "loss": 0,
        "node": "NETCUP",
        "speed": 439,
        "time": "2025-10-03 04:19:51"
    },
    {
        "colo": "Default",
        "ip": "2606:4700:11:5aaf:536:69d8:7500:aae6",
        "latency": 4,
        "line": "CU",
        "loss": 0,
        "node": "NETCUP",
        "speed": 425,
        "time": "2025-10-03 04:19:51"
    },
    {
        "colo": "Default",
        "ip": "2606:4700:11:ac73:fe7b:36e4:cf0f:6721",
        "latency": 4,
        "line": "CU",
        "loss": 0,
        "node": "NETCUP",
        "speed": 406,
        "time": "2025-10-03 04:19:51"
    }
]